.gitignore
LICENSE.txt
README.rst
setup.py
r00auth/__init__.py
r00auth.egg-info/PKG-INFO
r00auth.egg-info/SOURCES.txt
r00auth.egg-info/dependency_links.txt
r00auth.egg-info/top_level.txt